argilla_llama_index/__init__.py
argilla_llama_index/helpers.py
argilla_llama_index/llama_index_handler.py
argilla_llama_index-2.1.0.dist-info/METADATA
argilla_llama_index-2.1.0.dist-info/WHEEL
argilla_llama_index-2.1.0.dist-info/licenses/LICENSE
argilla_llama_index-2.1.0.dist-info/licenses/LICENSE_HEADER
argilla_llama_index-2.1.0.dist-info/RECORD
