Metadata-Version: 2.3
Name: argilla-llama-index
Version: 2.1.0
Summary: Argilla-LlamaIndex Integration
Project-URL: Documentation, https://github.com/argilla-io/argilla-llama-index
Project-URL: Issues, https://github.com/argilla-io/argilla-llama-index/issues
Project-URL: Source, https://github.com/argilla-io/argilla-llama-index
Author-email: Argilla <admin@argilla.io>
License-Expression: MIT
License-File: LICENSE
License-File: LICENSE_HEADER
Keywords: annotation,llm,monitoring
Classifier: Programming Language :: Python
Classifier: Programming Language :: Python :: 3.9
Classifier: Programming Language :: Python :: 3.10
Classifier: Programming Language :: Python :: 3.11
Requires-Python: >=3.8
Requires-Dist: argilla<3.0.0,>=2.2.0
Requires-Dist: llama-index<1.0,>=0.10.20
Requires-Dist: markdown>=3.6.0
Requires-Dist: packaging>=23.2
Requires-Dist: typing-extensions>=4.3.0
Provides-Extra: dev
Requires-Dist: black==23.10.0; extra == 'dev'
Requires-Dist: pre-commit>=3.5.0; extra == 'dev'
Requires-Dist: ruff==0.1.0; extra == 'dev'
Provides-Extra: tests
Requires-Dist: pytest>=7.4.0; extra == 'tests'
